laboratorium_2/4_alu/4_alu.v
module alu #(
  parameter W = 4
)
(
  input [W-1:0]       A,
  input [W-1:0]       B,
  input [1:0]         OP,
  input               Ci,
  output reg [W-1:0]  Y, //zamiast: output [W-1:0] Y; reg [W-1:0] Y;
  output reg          Co,
  output              Z
);

//always @(*) //* oznacza wszystkie wejscia
always @(A or B or Ci or OP)
begin
  case(OP)
    2'b00:
			begin
      	Y = A & B; Co = 1'b0;
    	end
    2'b01:
			begin
      	Y = A | B; Co = 1'b0;
    	end
    2'b10: {Co,Y} = A + B + Ci;
    2'b11: {Co,Y} = A - B - Ci;		
  endcase	
end

assign Z = ~|Y;	

endmodule

//zadania:
//1 symulacja behawioralna
//2 implementacja

//Co to jest Z? Rola Co w operacjach logicznych?

laboratorium_2/4_alu/4_alu_tb.v
`timescale 1ns / 1ps

module alu_tb;

parameter W = 16;

reg [W-1:0] A,B;
reg Ci;
wire [W-1:0] Y;
wire Co,Z;
reg [1:0] OP;

alu #(
  .W(W)
)
A1
(
  .A(A),
  .B(B),
  .Ci(Ci),
  .Y(Y),
  .Co(Co),
  .Z(Z),
  .OP(OP)
);

initial begin
  A = 16'd0; B = 16'd0; OP = 2'b00; Ci = 1'b0;
  #10; A = 16'h05FA; B = 16'hF505;
  repeat(4) begin			
    #10 Ci = 1'b1;
    #10 Ci = 1'b0;
    OP = OP + 1;		
  end
  $finish;	//po symulacji nie wychodzic z isim'a
end

initial begin
	$dumpfile("alu.vcd");
	$dumpvars();	
end

endmodule

laboratorium_2/4_alu/alu.vcd
$date
	Wed Apr 03 11:42:43 2024
$end
$version
	Icarus Verilog
$end
$timescale
	1ps
$end
$scope module alu_tb $end
$var wire 1 ! Z $end
$var wire 16 " Y [15:0] $end
$var wire 1 # Co $end
$var parameter 32 $ W $end
$var reg 16 % A [15:0] $end
$var reg 16 & B [15:0] $end
$var reg 1 ' Ci $end
$var reg 2 ( OP [1:0] $end
$scope module A1 $end
$var wire 16 ) A [15:0] $end
$var wire 16 * B [15:0] $end
$var wire 1 ' Ci $end
$var wire 2 + OP [1:0] $end
$var wire 1 ! Z $end
$var parameter 32 , W $end
$var reg 1 # Co $end
$var reg 16 - Y [15:0] $end
$upscope $end
$upscope $end
$enddefinitions $end
$comment Show the parameter values. $end
$dumpall
b10000 ,
b10000 $
$end
#0
$dumpvars
b0 -
b0 +
b0 *
b0 )
b0 (
0'
b0 &
b0 %
0#
b0 "
1!
$end
#10000
0!
b10100000000 "
b10100000000 -
b1111010100000101 &
b1111010100000101 *
b10111111010 %
b10111111010 )
#20000
1'
#30000
b1111010111111111 "
b1111010111111111 -
b1 (
b1 +
0'
#40000
1'
#50000
b1111101011111111 "
b1111101011111111 -
b10 (
b10 +
0'
#60000
b1111101100000000 "
b1111101100000000 -
1'
#70000
1#
b1000011110101 "
b1000011110101 -
b11 (
b11 +
0'
#80000
b1000011110100 "
b1000011110100 -
1'
#90000
0#
b10100000000 "
b10100000000 -
b0 (
b0 +
0'
