laboratorium_2/1_tristate_2/config.vh
parameter N = 3;

laboratorium_2/1_tristate_2/1_tri.v
module tri_st #(parameter N = 2)
(
  output reg[N-1:0] out,
  input        	  	en,
  input [N-1:0]     data
);

	always @(en or data)
  	if (en)
      out = data;
    else
      out = {N{1'bz}};

endmodule

//zadania:
//1 symulacja behawioralna
//2 zmienic we/wy na wektory
//3 sparametryzowac modul (opearator konkatencji)

laboratorium_2/1_tristate_2/1_tri_tb.v
`timescale 1ns / 100ps

module stimulus;

//`include "config.vh"
parameter N = 3;

reg          en;
reg [N-1:0]  data;
wire [N-1:0] out;

tri_st #(.N(N)) UUT (.en(en), .data(data), .out(out));

initial
	begin
		#0	en = 1'b0; data = {N{1'b0}};
		#5	en = 1'b1;
		#5	en = 1'b0;
		#5	repeat($pow(2, N)) #5 data = data + 1;
		#0	en = 1'b1;
		#5	repeat($pow(2, N)) #5 data = data + 1;
		#0	en = 1'b0;
		#5	$finish;
	end

initial
	begin
		$display("Symulacja bramki trojstanowej");
		$monitor("Czas: %t   Enable: %b Wejscie: %b Wyjscie: %b", $time, en, data, out);
		$dumpfile("tristate.vcd");
		$dumpvars(0, UUT);
	end

endmodule

//zadania:
//1 symulacja behawioralna
//2 zmienic we/wy na wektory
//3 sparametryzowac modul (opearator konkatencji)

laboratorium_2/1_tristate_2/tristate.vcd
$date
	Tue Apr 02 21:29:30 2024
$end
$version
	Icarus Verilog
$end
$timescale
	100ps
$end
$scope module stimulus $end
$scope module UUT $end
$var wire 3 ! data [2:0] $end
$var wire 1 " en $end
$var parameter 32 # N $end
$var reg 3 $ out [2:0] $end
$upscope $end
$upscope $end
$enddefinitions $end
$comment Show the parameter values. $end
$dumpall
b11 #
$end
#0
$dumpvars
bz $
0"
b0 !
$end
#50
b0 $
1"
#100
bz $
0"
#200
b1 !
#250
b10 !
#300
b11 !
#350
b100 !
#400
b101 !
#450
b110 !
#500
b111 !
#550
b0 $
1"
b0 !
#650
b1 $
b1 !
#700
b10 $
b10 !
#750
b11 $
b11 !
#800
b100 $
b100 !
#850
b101 $
b101 !
#900
b110 $
b110 !
#950
b111 $
b111 !
#1000
0"
bz $
b0 !
