laboratorium_3/3_licznik_bcd_2/3_licznik_bcd_ceo.v
module CNT(
  input             CLK,
  input             CLR,
  input             CE,
  output reg [3:0]  Q,
  output reg        CEO
);

always @(posedge CLK or posedge CLR)
  if(CLR)	begin
    	Q <= 4'd0;
			CEO <= 1'b0;
		end
  else begin
    if(CE) begin
      if(Q != 4'd9) begin
					Q <= Q + 1;
					//CEO <= 1'b0;
				end
      else begin
        	Q <= 4'd0;
					//CEO <=1'b1;
				end

			if (Q == 4'd8)
				#0.1 CEO <= 1'b1;
			else
				#0.1 CEO <= 1'b0;
    end
  end

//assign CEO = CE & (Q == 4'd9);

endmodule

//zadania:
//1 napisac tb + symulacja

//!!! zbadac wplyw CE; jak dziala CEO?

//2 zrealizowac CEO synchronicznie - przy generowaniu stanu Q
//3 dodac opoznienia do przypisania

//!!! jaka jest roznica pomiedzy realizacja 1 i 2 (ew. 3)

//4 zrealizowac polaczenie kaskadowe dwoch sekcji licznika bcd; przeniesienie ma byc zegarem nastepnej sekcji

//!!! wnioski

//5 realizacja synchroniczna --- specyfika ukladow FPGA; SKEW

laboratorium_3/3_licznik_bcd_5/3_licznik_bcd_ceo_tb.v
`timescale 1ns / 1ps

module test;

reg        clk;
wire       clk2;
reg        clr;
reg        ce;
wire [7:0] q;
wire       ceo1;
wire       ceo2;

CNT CNT1(.CLK(clk), .CLR(clr), .CE(ce), .Q(q[3:0]), .CEO(ceo1));
CNT CNT2(.CLK(clk2), .CLR(clr), .CE(ceo1), .Q(q[7:4]), .CEO(ceo2));

assign #0.1 clk2 = clk;

initial
	begin
		#0   clk = 0; clr = 1; ce = 0;
		#10           clr = 0; ce = 1;
		#20                    ce = 0;
		#20                    ce = 1;
		#100 $finish;
	end

initial
	begin
		forever #1 clk = ~clk;
	end

initial
	begin
		$display("Time     clk clr ce  q3q2q1q0 ceo");
		$timeformat(-9, 0, "ns", 6);
		$monitor("%t     %b  %b  %b     %b    %b", $time, clk, clr, ce, q, ceo1);
		$dumpfile("cnt_bcd_ceo.vcd");
		$dumpvars(0, test);
	end

endmodule

laboratorium_3/3_licznik_bcd_2/cnt_bcd_ceo.vcd
$date
	Tue Apr 09 10:22:48 2024
$end
$version
	Icarus Verilog
$end
$timescale
	1ps
$end
$scope module test $end
$scope module UUT $end
$var wire 1 ! CE $end
$var wire 1 " CLK $end
$var wire 1 # CLR $end
$var reg 1 $ CEO $end
$var reg 4 % Q [3:0] $end
$upscope $end
$upscope $end
$enddefinitions $end
$comment Show the parameter values. $end
$dumpall
$end
#0
$dumpvars
b0 %
0$
1#
0"
0!
$end
#1000
1"
#2000
0"
#3000
1"
#4000
0"
#5000
1"
#6000
0"
#7000
1"
#8000
0"
#9000
1"
#10000
0"
1!
0#
#11000
b1 %
1"
#12000
0"
#13000
b10 %
1"
#14000
0"
#15000
b11 %
1"
#16000
0"
#17000
b100 %
1"
#18000
0"
#19000
b101 %
1"
#20000
0"
#21000
b110 %
1"
#22000
0"
#23000
b111 %
1"
#24000
0"
#25000
b1000 %
1"
#26000
0"
#27000
b1001 %
1"
#27100
1$
#28000
0"
#29000
b0 %
1"
#29100
0$
#30000
0"
0!
#31000
1"
#32000
0"
#33000
1"
#34000
0"
#35000
1"
#36000
0"
#37000
1"
#38000
0"
#39000
1"
#40000
0"
#41000
1"
#42000
0"
#43000
1"
#44000
0"
#45000
1"
#46000
0"
#47000
1"
#48000
0"
#49000
1"
#50000
0"
1!
#51000
b1 %
1"
#52000
0"
#53000
b10 %
1"
#54000
0"
#55000
b11 %
1"
#56000
0"
#57000
b100 %
1"
#58000
0"
#59000
b101 %
1"
#60000
0"
#61000
b110 %
1"
#62000
0"
#63000
b111 %
1"
#64000
0"
#65000
b1000 %
1"
#66000
0"
#67000
b1001 %
1"
#67100
1$
#68000
0"
#69000
b0 %
1"
#69100
0$
#70000
0"
#71000
b1 %
1"
#72000
0"
#73000
b10 %
1"
#74000
0"
#75000
b11 %
1"
#76000
0"
#77000
b100 %
1"
#78000
0"
#79000
b101 %
1"
#80000
0"
#81000
b110 %
1"
#82000
0"
#83000
b111 %
1"
#84000
0"
#85000
b1000 %
1"
#86000
0"
#87000
b1001 %
1"
#87100
1$
#88000
0"
#89000
b0 %
1"
#89100
0$
#90000
0"
#91000
b1 %
1"
#92000
0"
#93000
b10 %
1"
#94000
0"
#95000
b11 %
1"
#96000
0"
#97000
b100 %
1"
#98000
0"
#99000
b101 %
1"
#100000
0"
#101000
b110 %
1"
#102000
0"
#103000
b111 %
1"
#104000
0"
#105000
b1000 %
1"
#106000
0"
#107000
b1001 %
1"
#107100
1$
#108000
0"
#109000
b0 %
1"
#109100
0$
#110000
0"
#111000
b1 %
1"
#112000
0"
#113000
b10 %
1"
#114000
0"
#115000
b11 %
1"
#116000
0"
#117000
b100 %
1"
#118000
0"
#119000
b101 %
1"
#120000
0"
#121000
b110 %
1"
#122000
0"
#123000
b111 %
1"
#124000
0"
#125000
b1000 %
1"
#126000
0"
#127000
b1001 %
1"
#127100
1$
#128000
0"
#129000
b0 %
1"
#129100
0$
#130000
0"
#131000
b1 %
1"
#132000
0"
#133000
b10 %
1"
#134000
0"
#135000
b11 %
1"
#136000
0"
#137000
b100 %
1"
#138000
0"
#139000
b101 %
1"
#140000
0"
#141000
b110 %
1"
#142000
0"
#143000
b111 %
1"
#144000
0"
#145000
b1000 %
1"
#146000
0"
#147000
b1001 %
1"
#147100
1$
#148000
0"
#149000
b0 %
1"
#149100
0$
