laboratorium_1/5_komparator_3/5_komparator.v

module komparator(IN1, IN2, inEQ, inGT, inLT, outEQ, outGT, outLT);
	input [1:0] IN1, IN2;
	input inEQ, inGT, inLT;
	output wire outEQ, outGT, outLT;

	assign outGT = inGT | (inEQ & (IN1 > IN2));
	assign outLT = inLT | (inEQ & (IN1 < IN2));
	assign outEQ = ~(outGT | outLT);

endmodule

//zadania:
//1 implementacja
//2 zrealizowac komparator z wyjsciami I1>I2, I1=I2, I1<I2
/*
        |  |        |  |
       _|  |_      _|  |_
       \    /      \    /
        \  /        \  /
     +--------------------+
     |                    |
     |                  > +------
     |                  = +------
     |                  < +------
     |                    |
     +--------------------+
*/
//3 zrealizowac komparator kaskadowy z wejsciani/wyjsciami I1>I2, I1=I2, I1<I2
/*
        |  |        |  |
       _|  |_      _|  |_
       \    /      \    /
        \  /        \  /
     +--------------------+
     |                    |
-----+ >                > +------
-----+ =                = +------
-----+ <                < +------
     |                    |
     +--------------------+
*/

laboratorium_1/5_komparator_3/5_komparator_tb.v
`timescale 1ns / 100ps

module test;

reg [1:0] in1;
reg [1:0] in2;
reg				in_eq, in_gt, in_lt;
wire      out_eq, out_gt, out_lt;

komparator UUT(.IN1(in1), .IN2(in2),
							 .inEQ(in_eq), .inGT(in_gt), .inLT(in_lt),
               .outEQ(out_eq), .outGT(out_gt), .outLT(out_lt));

initial
	begin
		in_eq = 1; in_gt = 0; in_lt = 0;
		in1 = 0; in2 = 0;
		repeat(16)
			#5 {in2, in1} = {in2, in1} + 1;

		in_eq = 0; in_gt = 1; in_lt = 0;
		in1 = 0; in2 = 0;
		repeat(16)
			#5 {in2, in1} = {in2, in1} + 1;

		in_eq = 0; in_gt = 0; in_lt = 1;
		in1 = 0; in2 = 0;
		repeat(16)
			#5 {in2, in1} = {in2, in1} + 1;

		$finish;
	end

initial
	begin
		$timeformat(-9, 0, "ns", 6);
		$monitor("Time: %t   IN1: %d  IN2: %d  in_gt: %b  in_eq: %b  in_lt: %b    out_gt: %b  out_eq: %b  out_lt: %b",
		         $time, in1, in2, in_gt, in_eq, in_lt, out_gt, out_eq, out_lt);
	end

initial
	begin
		$dumpfile("komparator.vcd");
		$dumpvars(0, UUT);
	end

endmodule

laboratorium_1/5_komparator_3/komparator.vcd
$date
	Mon Apr 01 18:38:15 2024
$end
$version
	Icarus Verilog
$end
$timescale
	100ps
$end
$scope module test $end
$scope module UUT $end
$var wire 2 ! IN1 [1:0] $end
$var wire 2 " IN2 [1:0] $end
$var wire 1 # inEQ $end
$var wire 1 $ inGT $end
$var wire 1 % inLT $end
$var wire 1 & outEQ $end
$var wire 1 ' outGT $end
$var wire 1 ( outLT $end
$upscope $end
$upscope $end
$enddefinitions $end
$comment Show the parameter values. $end
$dumpall
$end
#0
$dumpvars
0(
0'
1&
0%
0$
1#
b0 "
b0 !
$end
#50
0&
1'
b1 !
#100
b10 !
#150
b11 !
#200
1(
0'
b1 "
b0 !
#250
1&
0(
b1 !
#300
0&
1'
b10 !
#350
b11 !
#400
0'
1(
b10 "
b0 !
#450
b1 !
#500
1&
0(
b10 !
#550
0&
1'
b11 !
#600
0'
1(
b11 "
b0 !
#650
b1 !
#700
b10 !
#750
1&
0(
b11 !
#800
0&
1'
1$
0#
b0 "
b0 !
#850
b1 !
#900
b10 !
#950
b11 !
#1000
b1 "
b0 !
#1050
b1 !
#1100
b10 !
#1150
b11 !
#1200
b10 "
b0 !
#1250
b1 !
#1300
b10 !
#1350
b11 !
#1400
b11 "
b0 !
#1450
b1 !
#1500
b10 !
#1550
b11 !
#1600
1(
0'
1%
0$
b0 "
b0 !
#1650
b1 !
#1700
b10 !
#1750
b11 !
#1800
b1 "
b0 !
#1850
b1 !
#1900
b10 !
#1950
b11 !
#2000
b10 "
b0 !
#2050
b1 !
#2100
b10 !
#2150
b11 !
#2200
b11 "
b0 !
#2250
b1 !
#2300
b10 !
#2350
b11 !
#2400
b0 "
b0 !
