laboratorium_3/2_licznik_synchr/2_licznik_synchr.v
module CNT(
  input              CLK,
  input              CLR,
  output reg [3:0]   Q
);

always @(posedge CLK or posedge CLR)
  if(CLR)
    #0.5 Q <= 4'd0;
  else
    #0.5 Q <= Q + 1;

endmodule

//zadania:
//1 napisac tb + symulacja
//2 dodac opoznienie + symulacja
//3 symulacja PostRoute

laboratorium_3/2_licznik_synchr/2_licznik_synchr_tb.v
`timescale 1ns / 1ps

module test_cnt;

reg        clk;
reg        clr;
wire [3:0] q;

CNT UUT(.CLK(clk), .CLR(clr), .Q(q));

initial
		clk = 0;
always #10 clk = ~clk;

initial
	begin
		#0   clr = 1;
		#20	 clr = 0;
		#200 clr = 1;
		#250 clr = 0;
		#500 $finish;
	end

initial
	begin
		$monitor("Time: %t     clk: %b  clr: %b   q: %b", $time, clk, clr, q);
		$dumpfile("cnts.vcd");
		$dumpvars(0, UUT);
	end

endmodule

laboratorium_3/2_licznik_synchr/cnts.vcd
$date
	Thu Apr 18 16:26:52 2024
$end
$version
	Icarus Verilog
$end
$timescale
	1ps
$end
$scope module test_cnt $end
$scope module UUT $end
$var wire 1 ! CLK $end
$var wire 1 " CLR $end
$var reg 4 # Q [3:0] $end
$upscope $end
$upscope $end
$enddefinitions $end
$comment Show the parameter values. $end
$dumpall
$end
#0
$dumpvars
bx #
1"
0!
$end
#500
b0 #
#10000
1!
#20000
0!
0"
#30000
1!
#30500
b1 #
#40000
0!
#50000
1!
#50500
b10 #
#60000
0!
#70000
1!
#70500
b11 #
#80000
0!
#90000
1!
#90500
b100 #
#100000
0!
#110000
1!
#110500
b101 #
#120000
0!
#130000
1!
#130500
b110 #
#140000
0!
#150000
1!
#150500
b111 #
#160000
0!
#170000
1!
#170500
b1000 #
#180000
0!
#190000
1!
#190500
b1001 #
#200000
0!
#210000
1!
#210500
b1010 #
#220000
0!
1"
#220500
b0 #
#230000
1!
#240000
0!
#250000
1!
#260000
0!
#270000
1!
#280000
0!
#290000
1!
#300000
0!
#310000
1!
#320000
0!
#330000
1!
#340000
0!
#350000
1!
#360000
0!
#370000
1!
#380000
0!
#390000
1!
#400000
0!
#410000
1!
#420000
0!
#430000
1!
#440000
0!
#450000
1!
#460000
0!
#470000
1!
0"
#470500
b1 #
#480000
0!
#490000
1!
#490500
b10 #
#500000
0!
#510000
1!
#510500
b11 #
#520000
0!
#530000
1!
#530500
b100 #
#540000
0!
#550000
1!
#550500
b101 #
#560000
0!
#570000
1!
#570500
b110 #
#580000
0!
#590000
1!
#590500
b111 #
#600000
0!
#610000
1!
#610500
b1000 #
#620000
0!
#630000
1!
#630500
b1001 #
#640000
0!
#650000
1!
#650500
b1010 #
#660000
0!
#670000
1!
#670500
b1011 #
#680000
0!
#690000
1!
#690500
b1100 #
#700000
0!
#710000
1!
#710500
b1101 #
#720000
0!
#730000
1!
#730500
b1110 #
#740000
0!
#750000
1!
#750500
b1111 #
#760000
0!
#770000
1!
#770500
b0 #
#780000
0!
#790000
1!
#790500
b1 #
#800000
0!
#810000
1!
#810500
b10 #
#820000
0!
#830000
1!
#830500
b11 #
#840000
0!
#850000
1!
#850500
b100 #
#860000
0!
#870000
1!
#870500
b101 #
#880000
0!
#890000
1!
#890500
b110 #
#900000
0!
#910000
1!
#910500
b111 #
#920000
0!
#930000
1!
#930500
b1000 #
#940000
0!
#950000
1!
#950500
b1001 #
