laboratorium_1/6_demultiplekser/6_demux.v
module demux1to4(
	input						 A,
	input [1:0]      Sel,
  output reg [3:0] Y
);

  always @(*)
    case (Sel)
      2'b00   : Y <= {3'b0, A};
      2'b01   : Y <= {2'b0, A, 1'b0};
      2'b10   : Y <= {1'b0, A, 2'b0};
      2'b11   : Y <= {A, 3'b0};
      default : Y <= 4'b0000;
    endcase

endmodule

//zadania:
//1 wykorzystujac pomysl z 4_dekoder.v zrealizowac demultiplekser 1->4
/*
      +------+
      |     /|
      |    / |____
      |   /  |
      |  /   |
      | /    |____
______|/     |
      |\     |
      | \    |____
      |  \   |
      |   \  |
      |    \ |____
      |     \|
      +-+-+--+
        | |
        | |
*/
//2 wykorzystujac pomysl z 4_dekoder.v mozna zbudowac koder, transkoder

laboratorium_1/6_demultiplekser/6_demux_tb.v
`timescale 1ns / 100ps

module test;

reg        inA;
reg [1:0]  inSel;
wire [3:0] outY;

demux1to4 UUT(.A(inA), .Sel(inSel), .Y(outY));

initial
	begin
		#0 inA = 0; inSel = 0;

		repeat(8)
			#5 {inSel, inA} = {inSel, inA} + 1;

		$finish;
	end

initial
	begin
		$timeformat(-9, 0, "ns", 6);
		$display("Simulation results");
		$display("  Time  Sel A   Y3 Y2 Y1 Y0");
		$monitor("%t   %d  %b    %b  %b  %b  %b", $time, inSel, inA, outY[3], outY[2], outY[1], outY[0]);

		$dumpfile("demux.vcd");
		$dumpvars(0, UUT);
	end

endmodule

laboratorium_1/6_demultiplekser/demux.vcd
$date
	Mon Apr 01 19:11:38 2024
$end
$version
	Icarus Verilog
$end
$timescale
	100ps
$end
$scope module test $end
$scope module UUT $end
$var wire 1 ! A $end
$var wire 2 " Sel [1:0] $end
$var reg 4 # Y [3:0] $end
$upscope $end
$upscope $end
$enddefinitions $end
$comment Show the parameter values. $end
$dumpall
$end
#0
$dumpvars
b0 #
b0 "
0!
$end
#50
b1 #
1!
#100
b0 #
b1 "
0!
#150
b10 #
1!
#200
b0 #
b10 "
0!
#250
b100 #
1!
#300
b0 #
b11 "
0!
#350
b1000 #
1!
#400
b0 #
b0 "
0!
