laboratorium_1/5_komparator_2/5_komparator.v
/* wersja 1
module komparator(IN1, IN2, IN1_EQUAL_IN2, IN1_GREATER_IN2, IN1_LESS_IN2);
input [1:0] IN1, IN2;
output reg IN1_EQUAL_IN2, IN1_GREATER_IN2, IN1_LESS_IN2;

   always @(IN1 or IN2)
    if (IN1 > IN2)
	    IN1_GREATER_IN2 = 1'b1;
    else
			IN1_GREATER_IN2 = 1'b0;

   always @(IN1 or IN2)
    if (IN1 < IN2)
	    IN1_LESS_IN2 = 1'b1;
    else
			IN1_LESS_IN2 = 1'b0;

   always @(IN1 or IN2)
    if (IN1 == IN2)
	    IN1_EQUAL_IN2 = 1'b1;
    else
			IN1_EQUAL_IN2 = 1'b0;

endmodule
*/

module komparator(IN1, IN2, IN1_EQUAL_IN2, IN1_GREATER_IN2, IN1_LESS_IN2);
input [1:0] IN1, IN2;
output wire IN1_EQUAL_IN2, IN1_GREATER_IN2, IN1_LESS_IN2;

	assign IN1_GREATER_IN2 = (IN1 > IN2);
	assign IN1_LESS_IN2    = (IN1 < IN2);
	assign IN1_EQUAL_IN2   = ~(IN1_GREATER_IN2 | IN1_LESS_IN2);


endmodule

//zadania:
//1 implementacja
//2 zrealizowac komparator z wyjsciami I1>I2, I1=I2, I1<I2
/*
        |  |        |  |
       _|  |_      _|  |_
       \    /      \    /
        \  /        \  /
     +--------------------+
     |                    |
     |                  > +------
     |                  = +------
     |                  < +------
     |                    |
     +--------------------+
*/
//3 zrealizowac komparator kaskadowy z wejsciani/wyjsciami I1>I2, I1=I2, I1<I2
/*
        |  |        |  |
       _|  |_      _|  |_
       \    /      \    /
        \  /        \  /
     +--------------------+
     |                    |
-----+ >                > +------
-----+ =                = +------
-----+ <                < +------
     |                    |
     +--------------------+
*/

laboratorium_1/5_komparator_2/5_komparator_tb.v
`timescale 1ns / 100ps

module test;

reg [1:0] in1;
reg [1:0] in2;
wire      in1_equal_in2,
          in1_greater_in2,
					in1_less_in2;

komparator UUT(.IN1(in1), .IN2(in2),
               .IN1_EQUAL_IN2(in1_equal_in2),
							 .IN1_GREATER_IN2(in1_greater_in2),
							 .IN1_LESS_IN2(in1_less_in2));

initial
	begin
		in1 = 0; in2 = 0;
		repeat(20)
			#5 {in2, in1} = {in2, in1} + 1;
		$finish;
	end

initial
	begin
		$timeformat(-9, 0, "ns", 6);
		$monitor("Time: %t   IN1: %d  IN2: %d   IN1>IN2: %b  IN1=IN2: %b  IN1<IN2: %b",
		         $time, in1, in2, in1_greater_in2, in1_equal_in2, in1_less_in2);
	end

initial
	begin
		$dumpfile("komparator.vcd");
		$dumpvars(0, UUT);
	end

endmodule

laboratorium_1/5_komparator_2/komparator.vcd
$date
	Mon Apr 01 12:26:29 2024
$end
$version
	Icarus Verilog
$end
$timescale
	100ps
$end
$scope module test $end
$scope module UUT $end
$var wire 2 ! IN1 [1:0] $end
$var wire 1 " IN1_EQUAL_IN2 $end
$var wire 2 # IN2 [1:0] $end
$var wire 1 $ IN1_LESS_IN2 $end
$var wire 1 % IN1_GREATER_IN2 $end
$upscope $end
$upscope $end
$enddefinitions $end
$comment Show the parameter values. $end
$dumpall
$end
#0
$dumpvars
0%
0$
b0 #
1"
b0 !
$end
#50
0"
1%
b1 !
#100
b10 !
#150
b11 !
#200
1$
b1 #
0%
b0 !
#250
1"
0$
b1 !
#300
0"
1%
b10 !
#350
b11 !
#400
b10 #
0%
1$
b0 !
#450
b1 !
#500
1"
0$
b10 !
#550
0"
1%
b11 !
#600
b11 #
0%
1$
b0 !
#650
b1 !
#700
b10 !
#750
1"
0$
b11 !
#800
b0 #
0$
b0 !
#850
0"
1%
b1 !
#900
b10 !
#950
b11 !
#1000
1$
b1 #
0%
b0 !
