laboratorium_1/5_komparator_1/5_komparator.v
module komparator(IN1, IN2, OUT);
input [1:0] IN1, IN2;
output reg OUT;

   always @(IN1 or IN2)
      if (IN1 >= IN2)  //typ komparatora
	    OUT = 1'b1;
      else
		OUT = 1'b0;

endmodule

//zadania:
//1 implementacja
//2 zrealizowac komparator z wyjsciami I1>I2, I1=I2, I1<I2
/*
        |  |        |  |
       _|  |_      _|  |_
       \    /      \    /
        \  /        \  /
     +--------------------+
     |                    |
     |                  > +------
     |                  = +------
     |                  < +------
     |                    |
     +--------------------+
*/
//3 zrealizowac komparator kaskadowy z wejsciani/wyjsciami I1>I2, I1=I2, I1<I2
/*
        |  |        |  |
       _|  |_      _|  |_
       \    /      \    /
        \  /        \  /
     +--------------------+
     |                    |
-----+ >                > +------
-----+ =                = +------
-----+ <                < +------
     |                    |
     +--------------------+
*/

laboratorium_1/5_komparator_1/5_komparator_tb.v
`timescale 1ns / 100ps

module test;

reg [1:0] in1;
reg [1:0] in2;
wire      out;

komparator UUT(.IN1(in1), .IN2(in2), .OUT(out));

initial
	begin
		in1 = 0; in2 = 0;
		repeat(20)
			#5 {in2, in1} = {in2, in1} + 1;
		$finish;
	end

initial
	begin
		$timeformat(-9, 0, "ns", 6);
		$monitor("Time: %t   IN1: %d  IN2: %d   IN1>=IN2: %b", $time, in1, in2, out);
	end

initial
	begin
		$dumpfile("komparator.vcd");
		$dumpvars(0, UUT);
	end

endmodule

laboratorium_1/5_komparator_1/komparator.vcd
$date
	Mon Apr 01 12:18:57 2024
$end
$version
	Icarus Verilog
$end
$timescale
	100ps
$end
$scope module test $end
$scope module UUT $end
$var wire 2 ! IN1 [1:0] $end
$var wire 2 " IN2 [1:0] $end
$var reg 1 # OUT $end
$upscope $end
$upscope $end
$enddefinitions $end
$comment Show the parameter values. $end
$dumpall
$end
#0
$dumpvars
1#
b0 "
b0 !
$end
#50
b1 !
#100
b10 !
#150
b11 !
#200
0#
b1 "
b0 !
#250
1#
b1 !
#300
b10 !
#350
b11 !
#400
0#
b10 "
b0 !
#450
b1 !
#500
1#
b10 !
#550
b11 !
#600
0#
b11 "
b0 !
#650
b1 !
#700
b10 !
#750
1#
b11 !
#800
b0 "
b0 !
#850
b1 !
#900
b10 !
#950
b11 !
#1000
0#
b1 "
b0 !
