laboratorium_3/5_fsm_1/5_fsm_1.v
//automat wykrywajacy sekwencje 1011
module fsm(
	input 			CLK,
	input 			CLR,
	input 			CE,
	input 			IN,
	output reg  OUT
);

parameter st1 = 3'b000;
parameter st2 = 3'b001;
parameter st3 = 3'b110;
parameter st4 = 3'b111;
parameter st5 = 3'b100;

reg [2:0] state = st1;

   always@(posedge CLK)
	begin
      if (CLR) begin
         state <= st1;
         OUT <= 1'b0;
      end
      else
			if(CE) begin
				case (state)
					st1 :	begin
						if (IN == 1'b1)
							state <= st2;
						else
							state <= st1;
						OUT <= 0;
					end
					st2 :	begin
						if (IN == 1'b0)
							state <= st3;
						else
							state <= st2;
						OUT <= 1'b0;
					end
					st3 :	begin
						if (IN == 1'b1)
							state <= st4;
						else
							state <= st1;
						OUT <= 1'b0;
					end
					st4 :	begin
						if (IN == 1'b1)
							state <= st5;
						else
							state <= st3;
						OUT <= 1'b0;
					end
					st5 :	begin
						state <= st1;
						OUT <= 1'b1;
					end
					default : begin //domyslne przejscie - samokorekcja
						state <= st1;
						OUT <= 1'b0;
					end
				endcase
			end
	end
endmodule

//----------------------------
//zadania
//
//1. Napisac tb
//2. Sprawdzic dzialanie OUT

laboratorium_3/5_fsm_1/5_fsm_1_tb.v
`timescale 1ns / 1ps

module test_seq;

reg  clk;
reg  clr;
reg  ce;
reg  in;
wire out;

fsm UUT(.CLK(clk), .CLR(clr), .CE(ce), .IN(in), .OUT(out));

initial
	begin
		clk = 0;
		#50 $finish;
	end
always #1 clk = ~clk;

initial
	begin
		#0   clr = 1; ce = 1; in = 0;
		#10  clr = 0; ce = 1; in = 1;
		#2   clr = 0; ce = 1; in = 0;
		#2   clr = 0; ce = 1; in = 1;
		#2   clr = 0; ce = 1; in = 1;
		#10  clr = 0; ce = 1; in = 0;
		//forever #0.1 if (clk == 1) ce = 0; else ce = 1;
	end

initial
	begin
		$monitor("Time:%t   clk:%b clr:%b ce:%b in:%b  out:%b", $time, clk, clr, ce, in, out);
		$dumpfile("test_seq.vcd");
		$dumpvars(0, UUT);
	end

endmodule

laboratorium_3/5_fsm_1/test_seq.vcd
$date
	Wed Apr 10 18:34:55 2024
$end
$version
	Icarus Verilog
$end
$timescale
	1ps
$end
$scope module test_seq $end
$scope module UUT $end
$var wire 1 ! CE $end
$var wire 1 " CLK $end
$var wire 1 # CLR $end
$var wire 1 $ IN $end
$var parameter 3 % st1 $end
$var parameter 3 & st2 $end
$var parameter 3 ' st3 $end
$var parameter 3 ( st4 $end
$var parameter 3 ) st5 $end
$var reg 1 * OUT $end
$var reg 3 + state [2:0] $end
$upscope $end
$upscope $end
$enddefinitions $end
$comment Show the parameter values. $end
$dumpall
b100 )
b111 (
b110 '
b1 &
b0 %
$end
#0
$dumpvars
b0 +
x*
0$
1#
0"
1!
$end
#1000
0*
1"
#2000
0"
#3000
1"
#4000
0"
#5000
1"
#6000
0"
#7000
1"
#8000
0"
#9000
1"
#10000
0"
1$
0#
#11000
b1 +
1"
#12000
0"
0$
#13000
b110 +
1"
#14000
0"
1$
#15000
b111 +
1"
#16000
0"
#17000
b100 +
1"
#18000
0"
#19000
1*
b0 +
1"
#20000
0"
#21000
0*
b1 +
1"
#22000
0"
#23000
1"
#24000
0"
#25000
1"
#26000
0"
0$
#27000
b110 +
1"
#28000
0"
#29000
b0 +
1"
