laboratorium_1/3_dekoder/3_dekoder.v
module dekoder_2(
   input [2:0]       A,
   output reg [7:0]  Y
);

  always @(A)
  	case (A)
      3'b000  : Y <= 8'b00000001;
      3'b001  : Y <= 8'b00000010;
      3'b010  : Y <= 8'b00000100;
      3'b011  : Y <= 8'b00001000;
      3'b100  : Y <= 8'b00010000;
      3'b101  : Y <= 8'b00100000;
      3'b110  : Y <= 8'b01000000;
      3'b111  : Y <= 8'b10000000;
      default : Y <= 8'b00000000;
    endcase

endmodule

//zadania:
//1 implementacja

laboratorium_1/3_dekoder/3_dekoder_tb.v
`timescale 1ns / 100ps
module dekoder_tb;

reg  [2:0] input_A;
wire [7:0] output_Y;

dekoder_2 UUT(input_A, output_Y);

integer i; // definicja tutaj nie wymaga nazwy bloku

initial
	begin
		$display("Start simulation\n");
	  //integer i; // definicja w bloku wymaga jego nazwy czyli begin: nazwa
		input_A = 0;
		for (i = 0; i < 8; i = i + 1)
			begin
				//#5 input_A = input_A + 1;
				#5 input_A = i;
			end

		#5 $finish;
	end

initial
	begin
		$timeformat(-9, 0, "ns", 6);
		$monitor("Time= %t   Input= %d   Output= %b", $time, input_A, output_Y);
	end

initial
	begin
		$dumpfile("dekoder.vcd");
		$dumpvars(0, UUT);
	end

endmodule

laboratorium_1/3_dekoder/dekoder.vcd
$date
	Sun Mar 31 21:40:31 2024
$end
$version
	Icarus Verilog
$end
$timescale
	100ps
$end
$scope module dekoder_tb $end
$scope module UUT $end
$var wire 3 ! A [2:0] $end
$var reg 8 " Y [7:0] $end
$upscope $end
$upscope $end
$enddefinitions $end
$comment Show the parameter values. $end
$dumpall
$end
#0
$dumpvars
b1 "
b0 !
$end
#100
b10 "
b1 !
#150
b100 "
b10 !
#200
b1000 "
b11 !
#250
b10000 "
b100 !
#300
b100000 "
b101 !
#350
b1000000 "
b110 !
#400
b111 !
