laboratorium_3/4_rejestr_przes_3/4_rejestr_przes.v
module SHF_REG(
  input             CLK,
	input             CE,
  input             CLR,
  input             D,
  output reg [7:0]  Q
);

always @(posedge CLK or posedge CLR)
  if(CLR)
    Q <= 8'd0;
  else
		if(CE)
    	Q <= {Q[6:0],D};

endmodule

//zadania:
//1 uzale¿niæ rejestr od CE
//2 napisac tb + symulacja
//3 implementacja
//4 krazaca '1'

laboratorium_3/4_rejestr_przes_2/4_rejestr_przes_tb.v
`timescale 1ns / 1ps

module test_rej_przes;

reg        clk;
reg        ce;
reg        clr;
reg        d;
wire [7:0] q;

SHF_REG UUT(.CLK(clk), .CE(ce), .CLR(clr), .D(d), .Q(q));

initial
	begin
		clk = 1'b0;
		forever #1 clk = ~clk;
	end

initial
	begin
		#0  clr = 1'b1; ce = 1'b1; d = 1'b0;
		#5  clr = 1'b0; ce = 1'b1; d = 1'b0;
		#2  clr = 1'b0; ce = 1'b1; d = 1'b1;
		#10 clr = 1'b0; ce = 1'b0; d = 1'b1;
		#20 clr = 1'b0; ce = 1'b1; d = 1'b0;
		#20 clr = 1'b0; ce = 1'b1; d = 1'b0;
		#10 clr = 1'b0; ce = 1'b1; d = 1'b1;
		#5  clr = 1'b1; ce = 1'b1; d = 1'b0;
		#5  $finish;
	end

initial
	begin
		$monitor("Time: %t     clk:%b clr:%b d:%b  q:%b", $time, clk, clr, d, q);
		$dumpfile("shf_reg.vcd");
		$dumpvars(0, UUT);
	end

endmodule

//zadania:
//1 uzale¿niæ rejestr od CE
//2 napisac tb + symulacja
//3 implementacja
//4 krazaca '1'

laboratorium_3/4_rejestr_przes_2/shf_reg.vcd
$date
	Wed Apr 10 17:16:49 2024
$end
$version
	Icarus Verilog
$end
$timescale
	1ps
$end
$scope module test_rej_przes $end
$scope module UUT $end
$var wire 1 ! CE $end
$var wire 1 " CLK $end
$var wire 1 # CLR $end
$var wire 1 $ D $end
$var reg 8 % Q [7:0] $end
$upscope $end
$upscope $end
$enddefinitions $end
$comment Show the parameter values. $end
$dumpall
$end
#0
$dumpvars
b0 %
0$
1#
0"
1!
$end
#1000
1"
#2000
0"
#3000
1"
#4000
0"
#5000
1"
0#
#6000
0"
#7000
b1 %
1"
1$
#8000
0"
#9000
b11 %
1"
#10000
0"
#11000
b111 %
1"
#12000
0"
#13000
b1111 %
1"
#14000
0"
#15000
b11111 %
1"
#16000
0"
#17000
1"
0!
#18000
0"
#19000
1"
#20000
0"
#21000
1"
#22000
0"
#23000
1"
#24000
0"
#25000
1"
#26000
0"
#27000
1"
#28000
0"
#29000
1"
#30000
0"
#31000
1"
#32000
0"
#33000
1"
#34000
0"
#35000
1"
#36000
0"
#37000
b111110 %
1"
0$
1!
#38000
0"
#39000
b1111100 %
1"
#40000
0"
#41000
b11111000 %
1"
#42000
0"
#43000
b11110000 %
1"
#44000
0"
#45000
b11100000 %
1"
#46000
0"
#47000
b11000000 %
1"
#48000
0"
#49000
b10000000 %
1"
#50000
0"
#51000
b0 %
1"
#52000
0"
#53000
1"
#54000
0"
#55000
1"
#56000
0"
#57000
1"
#58000
0"
#59000
1"
#60000
0"
#61000
1"
#62000
0"
#63000
1"
#64000
0"
#65000
1"
#66000
0"
#67000
b1 %
1"
1$
#68000
0"
#69000
b11 %
1"
#70000
0"
#71000
b111 %
1"
#72000
b0 %
0"
0$
1#
