laboratorium_3/3_licznik_bcd_2/3_licznik_bcd_ceo.v
module CNT(
  input             CLK,
  input             CLR,
  input             CE,
  output reg [3:0]  Q,
  output reg        CEO
);

always @(posedge CLK or posedge CLR)
  if(CLR)	begin
    	Q <= 4'd0;
			CEO <= 1'b0;
		end
  else begin
    if(CE) begin
      if(Q != 4'd9) begin
					Q <= Q + 1;
					//CEO <= 1'b0;
				end
      else begin
        	Q <= 4'd0;
					//CEO <=1'b1;
				end

			if (Q == 4'd8)
				#0.1 CEO <= 1'b1;
			else
				#0.1 CEO <= 1'b0;
    end
  end

//assign CEO = CE & (Q == 4'd9);

endmodule

//zadania:
//1 napisac tb + symulacja

//!!! zbadac wplyw CE; jak dziala CEO?

//2 zrealizowac CEO synchronicznie - przy generowaniu stanu Q
//3 dodac opoznienia do przypisania

//!!! jaka jest roznica pomiedzy realizacja 1 i 2 (ew. 3)

//4 zrealizowac polaczenie kaskadowe dwoch sekcji licznika bcd; przeniesienie ma byc zegarem nastepnej sekcji

//!!! wnioski

//5 realizacja synchroniczna --- specyfika ukladow FPGA; SKEW

laboratorium_3/3_licznik_bcd_5/3_licznik_bcd_ceo_tb.v
`timescale 1ns / 1ps

module test;

reg        clk;
wire       clk2;
reg        clr;
reg        ce;
wire [7:0] q;
wire       ceo1;
wire       ceo2;

CNT CNT1(.CLK(clk), .CLR(clr), .CE(ce), .Q(q[3:0]), .CEO(ceo1));
CNT CNT2(.CLK(clk2), .CLR(clr), .CE(ceo1), .Q(q[7:4]), .CEO(ceo2));

assign #0.1 clk2 = clk;

initial
	begin
		#0   clk = 0; clr = 1; ce = 0;
		#10           clr = 0; ce = 1;
		#20                    ce = 0;
		#20                    ce = 1;
		#100 $finish;
	end

initial
	begin
		forever #1 clk = ~clk;
	end

initial
	begin
		$display("Time     clk clr ce  q3q2q1q0 ceo");
		$timeformat(-9, 0, "ns", 6);
		$monitor("%t     %b  %b  %b     %b    %b", $time, clk, clr, ce, q, ceo1);
		$dumpfile("cnt_bcd_ceo.vcd");
		$dumpvars(0, test);
	end

endmodule

laboratorium_3/3_licznik_bcd_5/cnt_bcd_ceo.vcd
$date
	Tue Apr 09 11:05:56 2024
$end
$version
	Icarus Verilog
$end
$timescale
	1ps
$end
$scope module test $end
$var wire 1 ! clk2 $end
$var wire 8 " q [7:0] $end
$var wire 1 # ceo2 $end
$var wire 1 $ ceo1 $end
$var reg 1 % ce $end
$var reg 1 & clk $end
$var reg 1 ' clr $end
$scope module CNT1 $end
$var wire 1 % CE $end
$var wire 1 $ CEO $end
$var wire 1 & CLK $end
$var wire 1 ' CLR $end
$var reg 4 ( Q [3:0] $end
$upscope $end
$scope module CNT2 $end
$var wire 1 $ CE $end
$var wire 1 # CEO $end
$var wire 1 ! CLK $end
$var wire 1 ' CLR $end
$var reg 4 ) Q [3:0] $end
$upscope $end
$upscope $end
$enddefinitions $end
$comment Show the parameter values. $end
$dumpall
$end
#0
$dumpvars
b0 )
b0 (
1'
0&
0%
x$
x#
b0 "
x!
$end
#100
0!
#200
0#
0$
#1000
1&
#1100
1!
#2000
0&
#2100
0!
#3000
1&
#3100
1!
#4000
0&
#4100
0!
#5000
1&
#5100
1!
#6000
0&
#6100
0!
#7000
1&
#7100
1!
#8000
0&
#8100
0!
#9000
1&
#9100
1!
#10000
0&
1%
0'
#10100
0!
#11000
b1 "
b1 (
1&
#11100
1!
#12000
0&
#12100
0!
#13000
b10 "
b10 (
1&
#13100
1!
#14000
0&
#14100
0!
#15000
b11 "
b11 (
1&
#15100
1!
#16000
0&
#16100
0!
#17000
b100 "
b100 (
1&
#17100
1!
#18000
0&
#18100
0!
#19000
b101 "
b101 (
1&
#19100
1!
#20000
0&
#20100
0!
#21000
b110 "
b110 (
1&
#21100
1!
#22000
0&
#22100
0!
#23000
b111 "
b111 (
1&
#23100
1!
#24000
0&
#24100
0!
#25000
b1000 "
b1000 (
1&
#25100
1!
#26000
0&
#26100
0!
#27000
b1001 "
b1001 (
1&
#27100
1!
#27200
1$
#28000
0&
#28100
0!
#29000
b0 "
b0 (
1&
#29100
b10000 "
b1 )
1!
#29200
0$
#30000
0&
0%
#30100
0!
#31000
1&
#31100
1!
#32000
0&
#32100
0!
#33000
1&
#33100
1!
#34000
0&
#34100
0!
#35000
1&
#35100
1!
#36000
0&
#36100
0!
#37000
1&
#37100
1!
#38000
0&
#38100
0!
#39000
1&
#39100
1!
#40000
0&
#40100
0!
#41000
1&
#41100
1!
#42000
0&
#42100
0!
#43000
1&
#43100
1!
#44000
0&
#44100
0!
#45000
1&
#45100
1!
#46000
0&
#46100
0!
#47000
1&
#47100
1!
#48000
0&
#48100
0!
#49000
1&
#49100
1!
#50000
0&
1%
#50100
0!
#51000
b10001 "
b1 (
1&
#51100
1!
#52000
0&
#52100
0!
#53000
b10010 "
b10 (
1&
#53100
1!
#54000
0&
#54100
0!
#55000
b10011 "
b11 (
1&
#55100
1!
#56000
0&
#56100
0!
#57000
b10100 "
b100 (
1&
#57100
1!
#58000
0&
#58100
0!
#59000
b10101 "
b101 (
1&
#59100
1!
#60000
0&
#60100
0!
#61000
b10110 "
b110 (
1&
#61100
1!
#62000
0&
#62100
0!
#63000
b10111 "
b111 (
1&
#63100
1!
#64000
0&
#64100
0!
#65000
b11000 "
b1000 (
1&
#65100
1!
#66000
0&
#66100
0!
#67000
b11001 "
b1001 (
1&
#67100
1!
#67200
1$
#68000
0&
#68100
0!
#69000
b10000 "
b0 (
1&
#69100
b100000 "
b10 )
1!
#69200
0$
#70000
0&
#70100
0!
#71000
b100001 "
b1 (
1&
#71100
1!
#72000
0&
#72100
0!
#73000
b100010 "
b10 (
1&
#73100
1!
#74000
0&
#74100
0!
#75000
b100011 "
b11 (
1&
#75100
1!
#76000
0&
#76100
0!
#77000
b100100 "
b100 (
1&
#77100
1!
#78000
0&
#78100
0!
#79000
b100101 "
b101 (
1&
#79100
1!
#80000
0&
#80100
0!
#81000
b100110 "
b110 (
1&
#81100
1!
#82000
0&
#82100
0!
#83000
b100111 "
b111 (
1&
#83100
1!
#84000
0&
#84100
0!
#85000
b101000 "
b1000 (
1&
#85100
1!
#86000
0&
#86100
0!
#87000
b101001 "
b1001 (
1&
#87100
1!
#87200
1$
#88000
0&
#88100
0!
#89000
b100000 "
b0 (
1&
#89100
b110000 "
b11 )
1!
#89200
0$
#90000
0&
#90100
0!
#91000
b110001 "
b1 (
1&
#91100
1!
#92000
0&
#92100
0!
#93000
b110010 "
b10 (
1&
#93100
1!
#94000
0&
#94100
0!
#95000
b110011 "
b11 (
1&
#95100
1!
#96000
0&
#96100
0!
#97000
b110100 "
b100 (
1&
#97100
1!
#98000
0&
#98100
0!
#99000
b110101 "
b101 (
1&
#99100
1!
#100000
0&
#100100
0!
#101000
b110110 "
b110 (
1&
#101100
1!
#102000
0&
#102100
0!
#103000
b110111 "
b111 (
1&
#103100
1!
#104000
0&
#104100
0!
#105000
b111000 "
b1000 (
1&
#105100
1!
#106000
0&
#106100
0!
#107000
b111001 "
b1001 (
1&
#107100
1!
#107200
1$
#108000
0&
#108100
0!
#109000
b110000 "
b0 (
1&
#109100
b1000000 "
b100 )
1!
#109200
0$
#110000
0&
#110100
0!
#111000
b1000001 "
b1 (
1&
#111100
1!
#112000
0&
#112100
0!
#113000
b1000010 "
b10 (
1&
#113100
1!
#114000
0&
#114100
0!
#115000
b1000011 "
b11 (
1&
#115100
1!
#116000
0&
#116100
0!
#117000
b1000100 "
b100 (
1&
#117100
1!
#118000
0&
#118100
0!
#119000
b1000101 "
b101 (
1&
#119100
1!
#120000
0&
#120100
0!
#121000
b1000110 "
b110 (
1&
#121100
1!
#122000
0&
#122100
0!
#123000
b1000111 "
b111 (
1&
#123100
1!
#124000
0&
#124100
0!
#125000
b1001000 "
b1000 (
1&
#125100
1!
#126000
0&
#126100
0!
#127000
b1001001 "
b1001 (
1&
#127100
1!
#127200
1$
#128000
0&
#128100
0!
#129000
b1000000 "
b0 (
1&
#129100
b1010000 "
b101 )
1!
#129200
0$
#130000
0&
#130100
0!
#131000
b1010001 "
b1 (
1&
#131100
1!
#132000
0&
#132100
0!
#133000
b1010010 "
b10 (
1&
#133100
1!
#134000
0&
#134100
0!
#135000
b1010011 "
b11 (
1&
#135100
1!
#136000
0&
#136100
0!
#137000
b1010100 "
b100 (
1&
#137100
1!
#138000
0&
#138100
0!
#139000
b1010101 "
b101 (
1&
#139100
1!
#140000
0&
#140100
0!
#141000
b1010110 "
b110 (
1&
#141100
1!
#142000
0&
#142100
0!
#143000
b1010111 "
b111 (
1&
#143100
1!
#144000
0&
#144100
0!
#145000
b1011000 "
b1000 (
1&
#145100
1!
#146000
0&
#146100
0!
#147000
b1011001 "
b1001 (
1&
#147100
1!
#147200
1$
#148000
0&
#148100
0!
#149000
b1010000 "
b0 (
1&
#149100
b1100000 "
b110 )
1!
#149200
0$
