laboratorium_1/1_mux/1_mux2x1to1x1.v
module mux2x1to1x1(input a, b, sel, output y);

assign y = (sel) ? b : a;

endmodule

//zadania:
//1 implementacja
//2 napisac MUX 2->1 dwubitowy + implementacja (wykorxzystujac instrukcje warunkowa)
//      +------+
//      |\     |
//___|\ | \    |
//     \|  \   |
//___  /|   \  |
//   |/ |    \ |
//      |     \|___|\ 
//            /|     \
//___|\ |    / |___  /
//     \|   /  |   |/
//___  /|  /   |
//   |/ | /    |
//      |/     |
//      +---+--+
//          |
//          |
			 
//3 napisac MUX 4->1 + implementacja (wykorxzystujac instrukcje warunkowa)

//      +------+
//      |\     |
//______| \    |
//      |  \   |
//______|   \  |
//      |    \ |
//      |     \|____ 
//______|     /|
//      |    / |
//      |   /  |
//______|  /   |
//      | /    |
//      |/     |
//      +-+-+--+
//        | |
//        | |

laboratorium_1/1_mux/1_mux2x1to1x1_tb.v
`timescale 1ns / 100ps

module mux2x1to1x1_tb;

reg A;
reg B;
reg Sel;
wire Y;

//mux2x1to1x1 UUT(A, B, Sel, Y);    // w kolejnosci wystepowania sygnalow
mux2x1to1x1 UUT(.a(A), .b(B), .sel(Sel), .y(Y));

initial
	begin
		#0		A = 0; B = 0;	Sel = 0;
		#5		A = 1;
		#5		A = 0;
		#5		B = 1;
		#5		B = 0;
		#5	Sel = 1;
		#5		A = 1;
		#5		A = 0;
		#5		B = 1;
		#5		B = 0;
		#5		$finish;
	end

initial
	$monitor($time, "A=%d B=%d Sel=%d     Y=%d", A, B, Sel, Y);

initial
  begin
    $dumpfile("mux2x1to1x1.vcd");
    $dumpvars(0, UUT);
  end


endmodule

laboratorium_1/1_mux/mux2x1to1x1.vcd
$date
	Sun Mar 31 13:23:15 2024
$end
$version
	Icarus Verilog
$end
$timescale
	100ps
$end
$scope module mux2x1to1x1_tb $end
$scope module UUT $end
$var wire 1 ! a $end
$var wire 1 " b $end
$var wire 1 # sel $end
$var wire 1 $ y $end
$upscope $end
$upscope $end
$enddefinitions $end
$comment Show the parameter values. $end
$dumpall
$end
#0
$dumpvars
0$
0#
0"
0!
$end
#50
1$
1!
#100
0$
0!
#150
1"
#200
0"
#250
1#
#300
1!
#350
0!
#400
1$
1"
#450
0$
0"
